abzu/__init__.py
abzu/__main__.py
abzu/kiss.py
abzu/textgen.py
abzu-0.0.1.dev0.dist-info/METADATA
abzu-0.0.1.dev0.dist-info/RECORD
abzu-0.0.1.dev0.dist-info/WHEEL
abzu-0.0.1.dev0.dist-info/entry_points.txt
abzu-0.0.1.dev0.dist-info/top_level.txt
resources/__init__.py
resources/colexifications.tsv
resources/consonant_inventories.tsv
resources/glosses.tsv
resources/phoneme_frequency.tsv
resources/syllable_patterns.tsv
resources/vowel_inventories.tsv
