Metadata-Version: 2.1
Name: abzu
Version: 0.0.1.dev0
Summary: System for the simulation of language evolution
Home-page: https://github.com/tresoldi/abzu
Author: Tiago Tresoldi
Author-email: tresoldi@shh.mpg.de
License: MIT
Keywords: linguistics,language evolution,simulation,conlang
Platform: UNKNOWN
Classifier: License :: OSI Approved :: MIT License
Classifier: Programming Language :: Python :: 3
Classifier: Operating System :: OS Independent
Classifier: Topic :: Software Development :: Libraries
Requires-Dist: ngesh
Requires-Dist: alteruphono
Requires-Dist: numpy
